Metadata-Version: 1.1
Name: rtapylysis
Version: 0.3
Summary: Synchrotorn Rapid Thermal Annealing (RTA) X-ray Diffraction (XRD) Data Analysis Project
Home-page: https://github.com/sdey135/rtapylysis
Author: SD
Author-email: sdey135@users.noreply.github.com
License: MIT
Download-URL: https://github.com/sdey135/rtapylysis/tarball/0.3
Keywords: Synchrotron,Rapid Thermal Annealing,RTA,X-ray Diffraction,XRD,Big Data
Platform: any
Classifier: Development Status :: 4 - Beta
Classifier: Intended Audience :: Science/Research
Classifier: Intended Audience :: Manufacturing
Classifier: Intended Audience :: Education
Classifier: License :: OSI Approved :: MIT License
Classifier: Natural Language :: English
Classifier: Operating System :: POSIX :: Linux
Classifier: Operating System :: Unix
Classifier: Operating System :: Microsoft :: Windows :: Windows 7
Classifier: Operating System :: MacOS
Classifier: Programming Language :: Python :: 2.7
Classifier: Programming Language :: Python :: 3
Classifier: Programming Language :: Python :: 3.3
Classifier: Programming Language :: Python :: 3.4
Classifier: Programming Language :: Python :: 3.5
Classifier: Topic :: Scientific/Engineering
Classifier: Topic :: Scientific/Engineering :: Physics
Classifier: Topic :: Software Development :: Build Tools
Classifier: Topic :: Education
